{
  "project_info": {
    "project_number": "1006655871501",
    "project_id": "reminders-sample",
    "storage_bucket": "reminders-sample.appspot.com"
  },
  "client": [
    {
      "client_info": {
        "mobilesdk_app_id": "1:1006655871501:android:cb59abb79786b2baad1344",
        "android_client_info": {
          "package_name": "com.example.reminders"
        }
      },
      "oauth_client": [
        {
          "client_id": "1006655871501-spksbc01itt39isujnqrig99h72r32e6.apps.googleusercontent.com",
          "client_type": 3
        }
      ],
      "api_key": [
        {
          "current_key": "AIzaSyCpc3tS97SZMS3N5QH4tUsGuEWBUyTHmJA"
        }
      ],
      "services": {
        "appinvite_service": {
          "other_platform_oauth_client": [
            {
              "client_id": "1006655871501-spksbc01itt39isujnqrig99h72r32e6.apps.googleusercontent.com",
              "client_type": 3
            }
          ]
        }
      }
    }
  ],
  "configuration_version": "1"
}